kingdon/__init__.py
kingdon/algebra.py
kingdon/codegen.py
kingdon/graph.js
kingdon/graph.py
kingdon/matrixreps.py
kingdon/multivector.py
kingdon/operator_dict.py
kingdon/polynomial.py
kingdon/taperecorder.py
kingdon-1.4.0.dist-info/AUTHORS.rst
kingdon-1.4.0.dist-info/LICENSE
kingdon-1.4.0.dist-info/METADATA
kingdon-1.4.0.dist-info/WHEEL
kingdon-1.4.0.dist-info/top_level.txt
kingdon-1.4.0.dist-info/RECORD
