Metadata-Version: 2.1
Name: kingdon
Version: 1.4.0
Summary: Pythonic Geometric Algebra Package
Home-page: https://github.com/tbuli/kingdon
Author: Martin Roelfs
Author-email: martinroelfs@yahoo.com
License: MIT license
Keywords: kingdon
Classifier: Development Status :: 2 - Pre-Alpha
Classifier: Intended Audience :: Developers
Classifier: License :: OSI Approved :: MIT License
Classifier: Natural Language :: English
Classifier: Programming Language :: Python :: 3
Classifier: Programming Language :: Python :: 3.8
Classifier: Programming Language :: Python :: 3.9
Classifier: Programming Language :: Python :: 3.10
Classifier: Programming Language :: Python :: 3.11
Classifier: Programming Language :: Python :: 3.12
Requires-Python: >=3.8
License-File: LICENSE
License-File: AUTHORS.rst
Requires-Dist: numpy
Requires-Dist: sympy
Requires-Dist: anywidget
